akshare_mcp/__init__.py
akshare_mcp/__main__.py
akshare_mcp/_version.py
akshare_mcp/config.py
akshare_mcp/server.py
akshare_mcp-0.1.2.dist-info/METADATA
akshare_mcp-0.1.2.dist-info/WHEEL
akshare_mcp-0.1.2.dist-info/licenses/LICENSE
akshare_mcp-0.1.2.dist-info/RECORD
