Metadata-Version: 2.4
Name: akshare_mcp
Version: 0.1.2
Summary: AKShare MCP Server
License-File: LICENSE
Requires-Python: >=3.10
Requires-Dist: akshare>=1.17.26
Requires-Dist: fastmcp>=2.10.6
